plot_reward_vs_steps-0.1.1.dist-info/licenses/LICENSE
plotrs/__init__.py
plotrs/plot.py
plot_reward_vs_steps-0.1.1.dist-info/METADATA
plot_reward_vs_steps-0.1.1.dist-info/WHEEL
plot_reward_vs_steps-0.1.1.dist-info/top_level.txt
plot_reward_vs_steps-0.1.1.dist-info/RECORD
