Metadata-Version: 2.4
Name: plot_reward_vs_steps
Version: 0.1.1
Summary: Simple RL reward plotting utility
Author-email: Shreeya Dutta <shreeya.dutta08@nmims.in>
License: MIT
Keywords: reinforcement-learning,plot,rewards,matplotlib,bandit
Requires-Python: >=3.7
License-File: LICENSE
Requires-Dist: matplotlib
Dynamic: license-file
